{"cameraMode":{"drawMode":0,"name":"Shaded","section":"Shading Mode"},"sceneLighting":true,"audioPlay":false,"sceneViewState":{"showFog":true,"showMaterialUpdate":false,"showSkybox":true,"showFlares":true,"showImageEffects":true,"showParticleSystems":true},"in2DMode":false,"pivot":{"x":-0.24836555123329163,"y":1.9389772415161133,"z":8.970603942871094},"rotation":{"x":0.022082194685935975,"y":-0.9716641306877136,"z":0.10092794895172119,"w":0.21259264647960664},"size":7.986549377441406,"orthographic":false}